{"cameraMode":{"drawMode":0,"name":"Shaded","section":"Shading Mode"},"sceneLighting":true,"audioPlay":false,"sceneViewState":{"showFog":true,"showMaterialUpdate":false,"showSkybox":true,"showFlares":true,"showImageEffects":true,"showParticleSystems":true},"in2DMode":false,"pivot":{"x":194.95986938476563,"y":4.585980415344238,"z":232.08209228515626},"rotation":{"x":-0.07195061445236206,"y":0.8835622072219849,"z":-0.14470383524894715,"w":-0.43963801860809328},"size":2.6363604068756105,"orthographic":false}